Workbook

Sheet Capacité
A1: Capacité d'Ahmed
A2: Paramètre | B2: Valeur | C2: Unité | D2: Source
A3: Heures brutes par semaine | B3: 12 | C3: h | D3: Donnée d'Ahmed
A4: Réserve gestion / prospection / support / imprévus | B4: 0.3 | C4: % | D4: Règle de planification n°3
A5: Capacité nette par semaine | B5: =B3*(1-B4) -> 8.4 | C5: h
A6: Semaines par sprint | B6: 2 | C6: sem. | D6: Règle n°5
A7: Capacité nette par sprint | B7: =B5*B6 -> 16.8 | C7: h
A8: Date de début du sprint 1 | B8: 46301 | D8: Mardi 6 octobre 2026, donnée d'Ahmed
A9: Marge sur intégrations externes | B9: 0.3 | C9: % | D9: Règle n°4, déjà incluse dans les estimations marquées « Externe »
A10: Budget mensuel outils/API | B10: 550 | C10: DH | D10: Donnée d'Ahmed
A12: Légende : cellules jaunes à texte bleu = hypothèses modifiables ; texte noir = formules ; texte vert = liens vers une autre feuille.

Sheet Backlog
A1: ID | B1: Jalon | C1: Story | D1: Sensible | E1: Externe (+30 % inclus) | F1: Sessions Claude Code | G1: Ahmed bas (h) | H1: Ahmed haut (h) | I1: Ahmed milieu (h) | J1: Sprint | K1: Statut | L1: Commentaire
A2: S0 | B2: 1 - Pilote centre | C2: Initialisation : Next.js, Supabase, CI, lint, i18n FR/AR avec RTL, fiches de décision | D2: Non | E2: Non | F2: 2 | G2: 3 | H2: 5 | I2: =(G2+H2)/2 -> 4 | J2: 1 | K2: À faire
A3: S1 | B3: 1 - Pilote centre | C3: Multi-établissement, auth, rôles (direction, caisse, enseignant, parent), RLS | D3: Oui | E3: Non | F3: 3 | G3: 5 | H3: 8 | I3: =(G3+H3)/2 -> 6.5 | J3: 1 | K3: À faire
A4: S2 | B4: 1 - Pilote centre | C4: Élèves, tuteurs, groupes/classes, inscriptions, import CSV | D4: Oui | E4: Non | F4: 3 | G4: 4 | H4: 7 | I4: =(G4+H4)/2 -> 5.5 | J4: 1 | K4: À faire
A5: S3 | B5: 1 - Pilote centre | C5: Absences : saisie enseignant, vue direction | D5: Non | E5: Non | F5: 2 | G5: 3 | H5: 5 | I5: =(G5+H5)/2 -> 4 | J5: 2 | K5: À faire
A6: S4 | B6: 1 - Pilote centre | C6: Notes simples : évaluations, saisie, consultation | D6: Non | E6: Non | F6: 2 | G6: 3 | H6: 5 | I6: =(G6+H6)/2 -> 4 | J6: 2 | K6: À faire
A7: S5 | B7: 1 - Pilote centre | C7: Plans tarifaires (forfait mensuel, par matière, annuel) et génération des échéances | D7: Oui | E7: Non | F7: 3 | G7: 5 | H7: 8 | I7: =(G7+H7)/2 -> 6.5 | J7: 2 | K7: À faire
A8: S6 | B8: 1 - Pilote centre | C8: Encaissement espèces : reçus numérotés, annulation motivée, clôture de caisse | D8: Oui | E8: Non | F8: 3 | G8: 5 | H8: 8 | I8: =(G8+H8)/2 -> 6.5 | J8: 3 | K8: À faire
A9: S7 | B9: 1 - Pilote centre | C9: Espace parent PWA : absences, notes, solde, reçus | D9: Non | E9: Non | F9: 3 | G9: 5 | H9: 8 | I9: =(G9+H9)/2 -> 6.5 | J9: 3 | K9: À faire
A10: S8 | B10: 1 - Pilote centre | C10: WhatsApp Cloud API : templates, webhooks, statuts, opt-in, coût par établissement | D10: Non | E10: Oui | F10: 3 | G10: 8 | H10: 13 | I10: =(G10+H10)/2 -> 10.5 | J10: 4 | K10: À faire
A11: S9 | B11: 1 - Pilote centre | C11: Relances intelligentes : règles J-3, J+1, J+7, langue du parent, arrêt dès le paiement | D11: Non | E11: Non | F11: 2 | G11: 4 | H11: 6 | I11: =(G11+H11)/2 -> 5 | J11: 4 | K11: À faire
A12: S10 | B12: 1 - Pilote centre | C12: Traduction FR, AR et darija des messages, validée par un humain avant envoi | D12: Non | E12: Oui | F12: 2 | G12: 5 | H12: 8 | I12: =(G12+H12)/2 -> 6.5 | J12: 5 | K12: À faire
A13: S11 | B13: 1 - Pilote centre | C13: Consentement des parents (CNDP), journal d'accès, mentions | D13: Oui | E13: Non | F13: 2 | G13: 3 | H13: 5 | I13: =(G13+H13)/2 -> 4 | J13: 5 | K13: À faire
... A19: S17 | B19: 2 - V1 écoles | C19: Messagerie dans l'application, traduction des réponses des parents | D19: Non | E19: Non | F19: 2 | G19: 4 | H19: 6 | I19: =(G19+H19)/2 -> 5 | J19: 8 | K19: À faire
C21: Total Jalon 1 | F21: =SUMIFS(F2:F19,$B$2:$B$19,"1 - Pilote centre") -> 31 | G21: =SUMIFS(G2:G19,$B$2:$B$19,"1 - Pilote centre") -> 56 | H21: =SUMIFS(H2:H19,$B$2:$B$19,"1 - Pilote centre") -> 91 | I21: =SUMIFS(I2:I19,$B$2:$B$19,"1 - Pilote centre") -> 73.5
C22: Total Jalon 2 | F22: =SUMIFS(F2:F19,$B$2:$B$19,"2 - V1 écoles") -> 14 | G22: =SUMIFS(G2:G19,$B$2:$B$19,"2 - V1 écoles") -> 33 | H22: =SUMIFS(H2:H19,$B$2:$B$19,"2 - V1 écoles") -> 54 | I22: =SUMIFS(I2:I19,$B$2:$B$19,"2 - V1 écoles") -> 43.5
C23: Total V1 | F23: =SUM(F2:F19) -> 45 | G23: =SUM(G2:G19) -> 89 | H23: =SUM(H2:H19) -> 145 | I23: =SUM(I2:I19) -> 117
C25: Statut : À faire / En cours / Fait / Bloqué / Coupé. Le temps d'Ahmed couvre lancer les prompts, relire, tester, corriger, déployer. Les stories « Externe » incluent déjà la marge de 30 %.

Sheet Planning
A1: Sprint | B1: Début | C1: Fin | D1: Stories | E1: Heures planifiées (milieu) | F1: Capacité nette | G1: Marge | H1: Heures fait | I1: Commentaire
A2: 1 | B2: =Capacité!$B$8+(1-1)*Capacité!$B$6*7 -> 46301 | C2: =B2+Capacité!$B$6*7-1 -> 46314 | D2: S0, S1, S2 | E2: =SUMIFS(Backlog!$I$2:$I$19,Backlog!$J$2:$J$19,A2) -> 16 | F2: =Capacité!$B$7 -> 16.8 | G2: =F2-E2 -> 0.8 | H2: =SUMIFS(Backlog!$I$2:$I$19,Backlog!$J$2:$J$19,A2,Backlog!$K$2:$K$19,"Fait") -> 0
A3: 2 | B3: =Capacité!$B$8+(2-1)*Capacité!$B$6*7 -> 46315 | C3: =B3+Capacité!$B$6*7-1 -> 46328 | D3: S3, S4, S5 | E3: =SUMIFS(Backlog!$I$2:$I$19,Backlog!$J$2:$J$19,A3) -> 14.5 | F3: =Capacité!$B$7 -> 16.8 | G3: =F3-E3 -> 2.3 | H3: =SUMIFS(Backlog!$I$2:$I$19,Backlog!$J$2:$J$19,A3,Backlog!$K$2:$K$19,"Fait") -> 0
A4: 3 | B4: =Capacité!$B$8+(3-1)*Capacité!$B$6*7 -> 46329 | C4: =B4+Capacité!$B$6*7-1 -> 46342 | D4: S6, S7 | E4: =SUMIFS(Backlog!$I$2:$I$19,Backlog!$J$2:$J$19,A4) -> 13 | F4: =Capacité!$B$7 -> 16.8 | G4: =F4-E4 -> 3.8 | H4: =SUMIFS(Backlog!$I$2:$I$19,Backlog!$J$2:$J$19,A4,Backlog!$K$2:$K$19,"Fait") -> 0
A5: 4 | B5: =Capacité!$B$8+(4-1)*Capacité!$B$6*7 -> 46343 | C5: =B5+Capacité!$B$6*7-1 -> 46356 | D5: S8, S9 | E5: =SUMIFS(Backlog!$I$2:$I$19,Backlog!$J$2:$J$19,A5) -> 15.5 | F5: =Capacité!$B$7 -> 16.8 | G5: =F5-E5 -> 1.3 | H5: =SUMIFS(Backlog!$I$2:$I$19,Backlog!$J$2:$J$19,A5,Backlog!$K$2:$K$19,"Fait") -> 0
A6: 5 | B6: =Capacité!$B$8+(5-1)*Capacité!$B$6*7 -> 46357 | C6: =B6+Capacité!$B$6*7-1 -> 46370 | D6: S10, S11, S12 + mise en service pilote | E6: =SUMIFS(Backlog!$I$2:$I$19,Backlog!$J$2:$J$19,A6) -> 14.5 | F6: =Capacité!$B$7 -> 16.8 | G6: =F6-E6 -> 2.3 | H6: =SUMIFS(Backlog!$I$2:$I$19,Backlog!$J$2:$J$19,A6,Backlog!$K$2:$K$19,"Fait") -> 0 | I6: Pilote du centre en service à la fin du sprint
A7: 6 | B7: =Capacité!$B$8+(6-1)*Capacité!$B$6*7 -> 46371 | C7: =B7+Capacité!$B$6*7-1 -> 46384 | D7: S13 (CMI) | E7: =SUMIFS(Backlog!$I$2:$I$19,Backlog!$J$2:$J$19,A7) -> 13 | F7: =Capacité!$B$7 -> 16.8 | G7: =F7-E7 -> 3.8 | H7: =SUMIFS(Backlog!$I$2:$I$19,Backlog!$J$2:$J$19,A7,Backlog!$K$2:$K$19,"Fait") -> 0 | I7: Coïncide avec le premier support du pilote
A8: 7 | B8: =Capacité!$B$8+(7-1)*Capacité!$B$6*7 -> 46385 | C8: =B8+Capacité!$B$6*7-1 -> 46398 | D8: S15, S14 | E8: =SUMIFS(Backlog!$I$2:$I$19,Backlog!$J$2:$J$19,A8) -> 16 | F8: =Capacité!$B$7 -> 16.8 | G8: =F8-E8 -> 0.8 | H8: =SUMIFS(Backlog!$I$2:$I$19,Backlog!$J$2:$J$19,A8,Backlog!$K$2:$K$19,"Fait") -> 0
A9: 8 | B9: =Capacité!$B$8+(8-1)*Capacité!$B$6*7 -> 46399 | C9: =B9+Capacité!$B$6*7-1 -> 46412 | D9: S16, S17 | E9: =SUMIFS(Backlog!$I$2:$I$19,Backlog!$J$2:$J$19,A9) -> 14.5 | F9: =Capacité!$B$7 -> 16.8 | G9: =F9-E9 -> 2.3 | H9: =SUMIFS(Backlog!$I$2:$I$19,Backlog!$J$2:$J$19,A9,Backlog!$K$2:$K$19,"Fait") -> 0
D10: Total | E10: =SUM(E2:E9) -> 117 | F10: =SUM(F2:F9) -> 134.4 | G10: =SUM(G2:G9) -> 17.4 | H10: =SUM(H2:H9) -> 0
A12: Scénarios sur 8 sprints
A13: Scénario | B13: Estimé (h) | C13: Capacité (h) | D13: Écart (h) | E13: Sprints nécessaires
A14: Bas | B14: =SUM(Backlog!G2:G19) -> 89 | C14: =Capacité!$B$7*8 -> 134.4 | D14: =C14-B14 -> 45.4 | E14: =B14/Capacité!$B$7 -> 5.297619
A15: Milieu | B15: =SUM(Backlog!I2:I19) -> 117 | C15: =Capacité!$B$7*8 -> 134.4 | D15: =C15-B15 -> 17.4 | E15: =B15/Capacité!$B$7 -> 6.9642857
A16: Haut | B16: =SUM(Backlog!H2:H19) -> 145 | C16: =Capacité!$B$7*8 -> 134.4 | D16: =C16-B16 -> -10.6 | E16: =B16/Capacité!$B$7 -> 8.6309524
A18: Écart positif = marge ; écart négatif (rouge) = dépassement à couvrir par les coupes (feuille Coupes).

Sheet Coupes
A1: Ordre | B1: Story | C1: Coupe proposée | D1: Gain bas (h) | E1: Gain haut (h) | F1: Appliquée ?
A2: 1 | B2: S14 | C2: SMS de secours reporté après la V1 (WhatsApp + PWA suffisent au pilote) | D2: 4 | E2: 7 | F2: Non
A3: 2 | B3: S17 | C3: Messagerie en lecture seule, sans échange dans les deux sens | D3: 3 | E3: 3 | F3: Non
A4: 3 | B4: S15 | C4: Assistant : FAQ structurée par intention plutôt que RAG, escalade humaine systématique | D4: 3 | E4: 3 | F4: Non
A5: 4 | B5: S4 | C5: Notes minimales pour le centre, bulletin déplacé en S16 | D5: 2 | E5: 2 | F5: Non
C6: Total gains possibles | D6: =SUM(D2:D5) -> 12 | E6: =SUM(E2:E5) -> 15
C8: Hors coupes : traduction en darija et relances (différenciateurs).

Sheet Démarches
A1: Démarche | B1: Lancer au sprint | C1: Bloque | D1: Statut | E1: Date de dépôt | F1: Commentaire
A2: Vérification Meta Business, compte WhatsApp Business et numéro | B2: 1 (cette semaine) | C2: S8 (sprint 4) | D2: À faire
A3: Soumission des templates WhatsApp (relance, reçu, absence) | B3: 3 | C3: S8, S9 | D3: À faire
A4: Dossier CNDP (données de mineurs, transfert éventuel hors du Maroc) | B4: 1 | C4: Mise en service (sprint 5) | D4: À faire | F4: Plus gros risque calendrier ; avis juridique recommandé
A5: Contact CMI ou banque pour le contrat marchand | B5: 1-2 | C5: S13 (sprint 6) | D5: À faire
A6: Consentement écrit des parents du centre | B6: 4 | C6: Import des vraies données (S12) | D6: À faire
A7: Contrat avec un fournisseur SMS | B7: 5 | C7: S14 | D7: À faire
A8: Prospection de 2 ou 3 écoles privées pilotes | B8: 3 et suivants | C8: Validation jalon 2 et Massar | D8: À faire
A9: Vérifier l'objet social de la SARL AU (édition de logiciels, services informatiques) | B9: 1 | C9: Meta, CMI | D9: À faire

Sheet Décisions
A1: # | B1: Décision à trancher | C1: Options | D1: Recommandation Claude | E1: Échéance | F1: Décision d'Ahmed
A2: 1 | B2: Découpage en deux jalons | C2: Pilote centre d'abord, CMI après mise en service / tout en un jalon | D2: Deux jalons | E2: Avant le sprint 1
A3: 2 | B3: Hébergement des données | C3: Supabase UE + autorisation de transfert CNDP / hébergeur au Maroc | D3: Supabase UE + autorisation | E3: Avant le dépôt CNDP (sprint 1)
A4: 3 | B4: Budget à la mise en service | C4: Augmenter le budget (~450 DH en plus) / faire payer le pilote dès décembre | D4: À trancher par Ahmed | E4: Avant le sprint 5
